d2animdata.py
d2animdata-0.2.1.dist-info/entry_points.txt
d2animdata-0.2.1.dist-info/LICENSE
d2animdata-0.2.1.dist-info/WHEEL
d2animdata-0.2.1.dist-info/METADATA
d2animdata-0.2.1.dist-info/RECORD
