Metadata-Version: 2.1
Name: d2animdata
Version: 0.2.1
Summary: Read, write, and convert AnimData.D2 to JSON & tabbed TXT (and vice versa).
Home-page: https://github.com/pastelmind/d2animdata
Author: pastelmind
Author-email: keepyourhonor@gmail.com
Requires-Python: >= 3.6
Classifier: Development Status :: 3 - Alpha
Classifier: Environment :: Console
Classifier: License :: OSI Approved :: MIT License
Classifier: Operating System :: OS Independent
Classifier: Programming Language :: Python
Classifier: Programming Language :: Python :: 3
Classifier: Programming Language :: Python :: 3.6
Classifier: Programming Language :: Python :: 3.7
Classifier: Programming Language :: Python :: 3.8
Classifier: Programming Language :: Python :: 3.9
Requires-Dist: dataclasses ~= 0.7; python_version < '3.7'
